perch/__init__.py
perch/cli.py
perch/commands/__init__.py
perch/commands/add.py
perch/commands/init.py
perch_py-0.1.3.dist-info/METADATA
perch_py-0.1.3.dist-info/WHEEL
perch_py-0.1.3.dist-info/entry_points.txt
perch_py-0.1.3.dist-info/licenses/LICENSE
perch_py-0.1.3.dist-info/RECORD
