Metadata-Version: 2.4
Name: perch-py
Version: 0.1.3
Summary: Perch is a developer-friendly CLI tool for scaffolding MCP HexLayer Architecture projects using clean structure and modular design.
Project-URL: Homepage, https://github.com/danielremoquillo/perch-py
Project-URL: Issues, https://github.com/danielremoquillo/perch-py
Author-email: Daniel Remoquillo <danielremoquillo.se@gmail.com>
License: MIT
License-File: LICENSE
Requires-Python: >=3.12
Requires-Dist: pydantic>=2.11.5
Requires-Dist: pyyaml>=6.0.2
Requires-Dist: rich>=14.0.0
Requires-Dist: twine>=6.1.0
Requires-Dist: typer>=0.16.0
